setup.py
SHICTHRSMACE/SHRMACE_Data.py
SHICTHRSMACE/SHRMACE_ErrorBase.py
SHICTHRSMACE/__init__.py
SHICTHRSMACE.egg-info/PKG-INFO
SHICTHRSMACE.egg-info/SOURCES.txt
SHICTHRSMACE.egg-info/dependency_links.txt
SHICTHRSMACE.egg-info/not-zip-safe
SHICTHRSMACE.egg-info/requires.txt
SHICTHRSMACE.egg-info/top_level.txt
SHICTHRSMACE/api/SHRMACE_get_cpu_id.py
SHICTHRSMACE/api/SHRMACE_get_cpu_info.py
SHICTHRSMACE/api/SHRMACE_get_cpu_vendor.py
SHICTHRSMACE/api/SHRMACE_get_disk_id.py
SHICTHRSMACE/api/SHRMACE_get_disk_info.py
SHICTHRSMACE/api/SHRMACE_get_gpu_id.py
SHICTHRSMACE/api/SHRMACE_get_gpu_info.py
SHICTHRSMACE/api/SHRMACE_get_mac_info.py
SHICTHRSMACE/api/SHRMACE_get_mb_id.py
SHICTHRSMACE/api/SHRMACE_get_mb_info.py
SHICTHRSMACE/api/SHRMACE_get_mem_info.py
SHICTHRSMACE/api/SHRMACE_get_pdc_id.py
SHICTHRSMACE/api/SHRMACE_get_system_info.py
SHICTHRSMACE/api/SHRMACE_get_uuid.py
SHICTHRSMACE/api/__init__.py
SHICTHRSMACE/utils/SHRMACE_dispatcher.py
SHICTHRSMACE/utils/__init__.py