Metadata-Version: 2.4
Name: SHICTHRSMACE
Version: 1.7.0
Summary: SHICTHRS MACE machine identity system
Home-page: https://github.com/JNTMTMTM/SHICTHRS_MACE
Author: SHICTHRS
Author-email: contact@shicthrs.com
License: GPL-3.0
Requires-Dist: colorama==0.4.6
Requires-Dist: pywin32==311
Requires-Dist: WMI==1.5.1
Dynamic: author
Dynamic: author-email
Dynamic: home-page
Dynamic: license
Dynamic: requires-dist
Dynamic: summary
